<?xml version="1.0"?>
<materi>
<judul> Dampak krisis energi </judul>
<html_format>Saat ini, sejumlah negara seperti di benua Eropa tengah mengalami krisis energi. Krisis energi terjadi lantaran beberapa negara telah mengalami pemulihan ekonomi selama pandemi Covid-19. Namun pemulihan ekonomi ini tidak dibarengi dengan pasokan energi yang memadai. Hal ini yang menyebabkan dampak krisis energi.  Berikut dampak krisis energi bagi negara yang mengalami. </html_format>
<gambar>mg1</gambar>
<html_format> kk2020p style="font-size:9px;text-align:center;font-style: italic;"> kk2020i> Gambar 29 Berita krisis energi 2021 di benua Eropa kk2020/i> kk2020/p></html_format>

<html_format>kk2020b>Pembatasan Harga Listrik dan Gas kk2020/b></html_format>
<html_format>Negara-negara di Eropa melakukan pembatasan harga listrik dan gas. Hal ini dilakukan untuk memperlambat kenaikan harga serta menghindari dampak yang mungkin timbul apabila harga mengalami kenaikan yang tidak terkendali. </html_format>

<html_format> kk2020b>Pemutusan Jaringan Listrik dan Gas kk2020/b></html_format>
<html_format>Rumah tangga di negara Eropa akan mengalami ancaman pemutusan jaringan listrik dan gas lantaran tidak dapat membayar tagihan. Banyak rumah tangga di Eropa yang akan mengalaminya karena di tengah pandemi Covid-19 ini pendapatan turun namun tagihan meningkat. Selain negara Eropa, China telah melakukan pemutusan listrik sejak September 2021. </html_format>

<html_format> kk2020b>Menggunakan Kembali Batu Bara sebagai Bahan Bakar Pembangkit Listrik kk2020/b></html_format>
<html_format>Negara-negara di Eropa kembali menggunakan batu bara sebagai bahan bakar pembangkit listrik. Hal ini karena pasokan gas yang minim dan harganya yang mahal. Diketahui negara negara Eropa sudah tidak menggunakan batu bara sebagai pembangkit listrik karena batu bara dinilai dapat merusak lingkungan</html_format>
</materi>
